<databaseChangeLog
        xmlns="http://www.liquibase.org/xml/ns/dbchangelog"
        xmlns:xsi="http://www.w3.org/2001/XMLSchema-instance"
        xsi:schemaLocation="
        http://www.liquibase.org/xml/ns/dbchangelog
        http://www.liquibase.org/xml/ns/dbchangelog/dbchangelog-3.8.xsd">

    <changeSet id="1" author="bala">
        <createTable tableName="wallet">
            <column name="id" type="VARCHAR(50)">
                <constraints primaryKey="true"/>
            </column>
            <column name="balance" type="DECIMAL"/>
            <column name="status" type="VARCHAR(20)"/>
        </createTable>
    </changeSet>
</databaseChangeLog>
